LICENSE
MANIFEST.in
README.rst
setup.cfg
setup.py
codebakers/__init__.py
codebakers/__main__.py
codebakers.egg-info/PKG-INFO
codebakers.egg-info/SOURCES.txt
codebakers.egg-info/dependency_links.txt
codebakers.egg-info/pbr.json
codebakers.egg-info/requires.txt
codebakers.egg-info/top_level.txt