Metadata-Version: 1.1
Name: codebakers
Version: 1.0.2
Summary: Zen of Codebakers
Home-page: https://github.com/aziontech/codebakers
Author: Mauricio de Abreu Antunes
Author-email: mauricio.antunes@azion.com
License: BSD
Platform: UNKNOWN
Classifier: Intended Audience :: Developers
Classifier: Operating System :: OS Independent
Classifier: Programming Language :: Python
